gitsum/__init__.py
gitsum/cli.py
gitsum/output.py
gitsum/search.py
gitsum/status.py
gitsum-1.1.0.dist-info/LICENSE.txt
gitsum-1.1.0.dist-info/METADATA
gitsum-1.1.0.dist-info/WHEEL
gitsum-1.1.0.dist-info/entry_points.txt
gitsum-1.1.0.dist-info/top_level.txt
gitsum-1.1.0.dist-info/RECORD
