Metadata-Version: 2.1
Name: gitsum
Version: 1.1.0
Summary: Summarize the status of multiple Git repositories.
Author-email: Louis Hildebrand <louis.hildebrand@mail.mcgill.ca>
License: MIT License
Project-URL: Bug Tracker, https://github.com/louis-hildebrand/gitsum/issues
Project-URL: Changelog, https://github.com/louis-hildebrand/gitsum/blob/main/CHANGELOG.md
Project-URL: Source, https://github.com/louis-hildebrand/gitsum
Keywords: git
Requires-Python: >=3.8
License-File: LICENSE.txt
Requires-Dist: pygit2
